fuzzyforest/__init__.py
fuzzyforest/model.py
fuzzyforest/selector.py
fuzzyforest-0.1.0.dist-info/METADATA
fuzzyforest-0.1.0.dist-info/WHEEL
fuzzyforest-0.1.0.dist-info/top_level.txt
fuzzyforest-0.1.0.dist-info/RECORD
