Metadata-Version: 2.4
Name: fuzzyforest
Version: 0.1.0
Summary: Fuzzy forest-style feature ranking using repeated random forests.
Author: Owen Cooper
License: MIT
Project-URL: Homepage, https://github.com/your-username/fuzzyforest
Keywords: feature selection,random forest,machine learning,sklearn
Requires-Python: >=3.9
Requires-Dist: numpy>=1.24
Requires-Dist: scikit-learn>=1.3
